code_sage/__init__.py
code_sage/middleware.py
code_sage/utils.py
code_sage-0.1.3.dist-info/LICENSE
code_sage-0.1.3.dist-info/METADATA
code_sage-0.1.3.dist-info/WHEEL
code_sage-0.1.3.dist-info/RECORD
